__init__.py
ycg.py
ycg-1.0.0.dist-info/METADATA
ycg-1.0.0.dist-info/WHEEL
ycg-1.0.0.dist-info/entry_points.txt
ycg-1.0.0.dist-info/top_level.txt
ycg-1.0.0.dist-info/RECORD
