Metadata-Version: 2.1
Name: ycg
Version: 1.0.0
Summary: ycg (yaml config generator) merges and templates yaml files
License: MIT License
Project-URL: Repository, https://github.com/racccoooon/ycg
Requires-Python: >=3.8
Requires-Dist: jinja2 >=3.1.4
Requires-Dist: pyyaml >=6.0.2
